{
    "key": "group_lc_button",
    "title": "LC Button",
    "fields": [
        {
            "key": "field_lc_button_name",
            "label": "LC Button",
            "name": "",
            "aria-label": "",
            "type": "message",
            "instructions": "",
            "required": 0,
            "conditional_logic": 0,
            "wrapper": {
                "width": "25",
                "class": "",
                "id": ""
            },
            "message": "",
            "new_lines": "wpautop",
            "esc_html": 0
        },
        {
            "key": "field_67e05fcc8e5a9",
            "label": "Link",
            "name": "link",
            "aria-label": "",
            "type": "link",
            "instructions": "",
            "required": 0,
            "conditional_logic": 0,
            "wrapper": {
                "width": "75",
                "class": "",
                "id": ""
            },
            "return_format": "array",
            "allow_in_bindings": 0
        }
    ],
    "location": [
        [
            {
                "param": "block",
                "operator": "==",
                "value": "acf\/lc-button"
            }
        ]
    ],
    "menu_order": 0,
    "position": "normal",
    "style": "default",
    "label_placement": "top",
    "instruction_placement": "label",
    "hide_on_screen": "",
    "active": true,
    "description": "Field group for LC Button block.",
    "show_in_rest": 0,
    "modified": 1742757853
}
